wasif_rag/__init__.py
wasif_rag/rag_pipeline.py
wasif_rag-0.0.3.dist-info/METADATA
wasif_rag-0.0.3.dist-info/WHEEL
wasif_rag-0.0.3.dist-info/top_level.txt
wasif_rag-0.0.3.dist-info/RECORD
